sgqlc/__init__.py
sgqlc/codegen/__init__.py
sgqlc/codegen/__main__.py
sgqlc/codegen/operation.py
sgqlc/codegen/schema.py
sgqlc/endpoint/__init__.py
sgqlc/endpoint/base.py
sgqlc/endpoint/http.py
sgqlc/endpoint/requests.py
sgqlc/endpoint/websocket.py
sgqlc/introspection/__init__.py
sgqlc/introspection/__main__.py
sgqlc/operation/__init__.py
sgqlc/types/__init__.py
sgqlc/types/datetime.py
sgqlc/types/relay.py
sgqlc/types/uuid.py
atlasai_sgqlc-16.3.dist-info/AUTHORS
atlasai_sgqlc-16.3.dist-info/LICENSE
atlasai_sgqlc-16.3.dist-info/METADATA
atlasai_sgqlc-16.3.dist-info/WHEEL
atlasai_sgqlc-16.3.dist-info/entry_points.txt
atlasai_sgqlc-16.3.dist-info/RECORD
